LICENSE
MANIFEST.in
README.md
requirements.txt
setup.cfg
setup.py
torchfcn/__init__.py
torchfcn/trainer.py
torchfcn/utils.py
torchfcn.egg-info/PKG-INFO
torchfcn.egg-info/SOURCES.txt
torchfcn.egg-info/dependency_links.txt
torchfcn.egg-info/requires.txt
torchfcn.egg-info/top_level.txt
torchfcn/datasets/__init__.py
torchfcn/datasets/voc.py
torchfcn/ext/fcn.berkeleyvision.org/README.md
torchfcn/ext/fcn.berkeleyvision.org/infer.py
torchfcn/ext/fcn.berkeleyvision.org/nyud_layers.py
torchfcn/ext/fcn.berkeleyvision.org/pascalcontext_layers.py
torchfcn/ext/fcn.berkeleyvision.org/score.py
torchfcn/ext/fcn.berkeleyvision.org/siftflow_layers.py
torchfcn/ext/fcn.berkeleyvision.org/surgery.py
torchfcn/ext/fcn.berkeleyvision.org/voc_helper.py
torchfcn/ext/fcn.berkeleyvision.org/voc_layers.py
torchfcn/ext/fcn.berkeleyvision.org/data/nyud/README.md
torchfcn/ext/fcn.berkeleyvision.org/data/nyud/classes.txt
torchfcn/ext/fcn.berkeleyvision.org/data/nyud/test.txt
torchfcn/ext/fcn.berkeleyvision.org/data/nyud/train.txt
torchfcn/ext/fcn.berkeleyvision.org/data/nyud/val.txt
torchfcn/ext/fcn.berkeleyvision.org/data/pascal/README.md
torchfcn/ext/fcn.berkeleyvision.org/data/pascal/classes.txt
torchfcn/ext/fcn.berkeleyvision.org/data/pascal/seg11valid.txt
torchfcn/ext/fcn.berkeleyvision.org/data/pascal-context/README.md
torchfcn/ext/fcn.berkeleyvision.org/data/pascal-context/classes-400.txt
torchfcn/ext/fcn.berkeleyvision.org/data/pascal-context/classes-59.txt
torchfcn/ext/fcn.berkeleyvision.org/data/sift-flow/README.md
torchfcn/ext/fcn.berkeleyvision.org/data/sift-flow/classes.txt
torchfcn/ext/fcn.berkeleyvision.org/data/sift-flow/test.txt
torchfcn/ext/fcn.berkeleyvision.org/data/sift-flow/trainval.txt
torchfcn/ext/fcn.berkeleyvision.org/ilsvrc-nets/README.md
torchfcn/ext/fcn.berkeleyvision.org/nyud-fcn32s-color/caffemodel-url
torchfcn/ext/fcn.berkeleyvision.org/nyud-fcn32s-color/net.py
torchfcn/ext/fcn.berkeleyvision.org/nyud-fcn32s-color/solve.py
torchfcn/ext/fcn.berkeleyvision.org/nyud-fcn32s-color/solver.prototxt
torchfcn/ext/fcn.berkeleyvision.org/nyud-fcn32s-color/test.prototxt
