Metadata-Version: 2.1
Name: torchfcn
Version: 1.9.7
Summary: PyTorch Implementation of Fully Convolutional Networks.
Home-page: https://github.com/wkentaro/pytorch-fcn
Author: Kentaro Wada
Author-email: www.kentaro.wada@gmail.com
License: MIT
Platform: UNKNOWN
Classifier: Development Status :: 5 - Production/Stable
Classifier: Intended Audience :: Developers
Classifier: Natural Language :: English
Classifier: License :: OSI Approved :: MIT License
Classifier: Programming Language :: Python
Classifier: Programming Language :: Python :: 2.7
Classifier: Programming Language :: Python :: 3.5
Classifier: Programming Language :: Python :: 3.6
Classifier: Programming Language :: Python :: 3.7
Classifier: Programming Language :: Python :: Implementation :: CPython
License-File: LICENSE
